{
    "gitSyncId": "6987b6eefc080202ca7dfe57_Setup_Empleados",
    "id": "EMPLEADOS_Setup_Empleados",
    "pluginId": "postgres-plugin",
    "pluginType": "DB",
    "unpublishedAction": {
        "actionConfiguration": {
            "body": "DROP TABLE IF EXISTS public.empleados;\n\nCREATE TABLE public.empleados (\n  id SERIAL PRIMARY KEY,\n  nombre TEXT NOT NULL,\n  apellidos TEXT DEFAULT '',\n  email TEXT DEFAULT '',\n  telefono TEXT DEFAULT '',\n  rol TEXT DEFAULT 'Técnico',\n  activo BOOLEAN DEFAULT TRUE,\n  created_at TIMESTAMPTZ DEFAULT NOW(),\n  updated_at TIMESTAMPTZ DEFAULT NOW()\n);\n",
            "encodeParamsToggle": true,
            "paginationType": "NONE",
            "pluginSpecifiedTemplates": [
                {
                    "value": true
                }
            ],
            "timeoutInMillisecond": 10000
        },
        "confirmBeforeExecute": false,
        "datasource": {
            "id": "postgres",
            "isAutoGenerated": false,
            "name": "postgres",
            "pluginId": "postgres-plugin"
        },
        "dynamicBindingPathList": [],
        "name": "Setup_Empleados",
        "pageId": "EMPLEADOS",
        "runBehaviour": "MANUAL",
        "userSetOnLoad": false
    }
}