{
    "gitSyncId": "Setup_Empleados_git_id",
    "id": "EMPLEADOS_Setup_Empleados",
    "pluginId": "postgres-plugin",
    "pluginType": "DB",
    "unpublishedAction": {
        "actionConfiguration": {
            "body": "CREATE TABLE IF NOT EXISTS public.empleados (\n  id SERIAL PRIMARY KEY,\n  nombre TEXT NOT NULL,\n  apellidos TEXT,\n  email TEXT,\n  telefono TEXT,\n  rol TEXT DEFAULT 'Técnico',\n  activo BOOLEAN DEFAULT TRUE,\n  created_at TIMESTAMPTZ DEFAULT NOW(),\n  updated_at TIMESTAMPTZ DEFAULT NOW()\n);\n\nCREATE OR REPLACE FUNCTION update_updated_at_column()\nRETURNS TRIGGER AS $$\nBEGIN\n    NEW.updated_at = NOW();\n    RETURN NEW;\nEND;\n$$ language 'plpgsql';\n\nDROP TRIGGER IF EXISTS update_empleados_updated_at ON public.empleados;\nCREATE TRIGGER update_empleados_updated_at\n    BEFORE UPDATE ON public.empleados\n    FOR EACH ROW\n    EXECUTE FUNCTION update_updated_at_column();\n",
            "encodeParamsToggle": true,
            "paginationType": "NONE",
            "pluginSpecifiedTemplates": [
                {
                    "value": true
                }
            ],
            "timeoutInMillisecond": 10000
        },
        "confirmBeforeExecute": false,
        "datasource": {
            "id": "postgres",
            "isAutoGenerated": false,
            "name": "postgres",
            "pluginId": "postgres-plugin"
        },
        "dynamicBindingPathList": [],
        "name": "Setup_Empleados",
        "pageId": "EMPLEADOS",
        "runBehaviour": "MANUAL",
        "userSetOnLoad": false
    }
}