{
  "gitSyncId": "6962c124dca6af427460bc22_7bb53909-5869-44da-a1ec-de6bb15ba341",
  "id": "ALBARANES FICHA_LogicaPrecios.crearLinea",
  "pluginId": "js-plugin",
  "pluginType": "JS",
  "unpublishedAction": {
    "actionConfiguration": {
      "encodeParamsToggle": true,
      "jsArguments": [
        {
          "name": "newRow"
        }
      ],
      "paginationType": "NONE",
      "timeoutInMillisecond": 10000
    },
    "collectionId": "ALBARANES FICHA_LogicaPrecios",
    "confirmBeforeExecute": false,
    "datasource": {
      "isAutoGenerated": false,
      "name": "UNUSED_DATASOURCE",
      "pluginId": "js-plugin"
    },
    "dynamicBindingPathList": [
      {
        "key": "body"
      }
    ],
    "fullyQualifiedName": "LogicaPrecios.crearLinea",
    "name": "crearLinea",
    "pageId": "ALBARANES FICHA",
    "runBehaviour": "MANUAL",
    "userSetOnLoad": false
  }
}