{
  "gitSyncId": "697682d9fc080202ca7df6d1_dbbfd017-a814-4f2e-98d4-ff4e81ad50ec",
  "id": "INCIDENCIAS_IncidenciaActions.sync",
  "pluginId": "js-plugin",
  "pluginType": "JS",
  "unpublishedAction": {
    "actionConfiguration": {
      "encodeParamsToggle": true,
      "jsArguments": [],
      "paginationType": "NONE",
      "timeoutInMillisecond": 10000
    },
    "collectionId": "INCIDENCIAS_IncidenciaActions",
    "confirmBeforeExecute": false,
    "datasource": {
      "isAutoGenerated": false,
      "name": "UNUSED_DATASOURCE",
      "pluginId": "js-plugin"
    },
    "dynamicBindingPathList": [
      {
        "key": "body"
      }
    ],
    "fullyQualifiedName": "IncidenciaActions.sync",
    "name": "sync",
    "pageId": "INCIDENCIAS",
    "runBehaviour": "MANUAL",
    "userSetOnLoad": false
  }
}