{
  "gitSyncId": "694ce73ebe5af016d4a63fd2_30fddccb-68aa-4458-a33a-7178271ed2ff",
  "id": "CLIENTES_ClientesJS.sincronizarClientesMasivo",
  "pluginId": "js-plugin",
  "pluginType": "JS",
  "unpublishedAction": {
    "actionConfiguration": {
      "encodeParamsToggle": true,
      "jsArguments": [],
      "paginationType": "NONE",
      "timeoutInMillisecond": 10000
    },
    "collectionId": "CLIENTES_ClientesJS",
    "confirmBeforeExecute": false,
    "datasource": {
      "isAutoGenerated": false,
      "name": "UNUSED_DATASOURCE",
      "pluginId": "js-plugin"
    },
    "dynamicBindingPathList": [
      {
        "key": "body"
      }
    ],
    "fullyQualifiedName": "ClientesJS.sincronizarClientesMasivo",
    "name": "sincronizarClientesMasivo",
    "pageId": "CLIENTES",
    "runBehaviour": "MANUAL",
    "userSetOnLoad": false
  }
}