{
  "animateLoading": true,
  "borderRadius": "{{appsmith.theme.borderRadius.appBorderRadius}}",
  "bottomRow": 90,
  "boxShadow": "none",
  "buttonColor": "{{appsmith.theme.colors.primaryColor}}",
  "buttonStyle": "PRIMARY",
  "buttonVariant": "SECONDARY",
  "disabledWhenInvalid": false,
  "dynamicBindingPathList": [
    {
      "key": "buttonColor"
    },
    {
      "key": "borderRadius"
    }
  ],
  "dynamicTriggerPathList": [
    {
      "key": "onClick"
    }
  ],
  "isDefaultClickDisabled": true,
  "isDisabled": false,
  "isLoading": false,
  "isVisible": true,
  "key": "upp9hi4b1e",
  "leftColumn": 47,
  "minWidth": 120,
  "mobileBottomRow": 22,
  "mobileLeftColumn": 31,
  "mobileRightColumn": 47,
  "mobileTopRow": 18,
  "needsErrorInfo": false,
  "onClick": "{{storeValue('editMode', false).then(() => closeModal(ModalDetalle.name))}}",
  "originalBottomRow": 23,
  "originalTopRow": 19,
  "parentId": "xfirhtgsix",
  "placement": "CENTER",
  "recaptchaType": "V3",
  "renderMode": "CANVAS",
  "resetFormOnClick": false,
  "responsiveBehavior": "hug",
  "rightColumn": 63,
  "text": "Close",
  "topRow": 86,
  "type": "BUTTON_WIDGET",
  "version": 1,
  "widgetId": "lq5xxu2fw8",
  "widgetName": "Button2"
}